tianmoucv/__init__.py
tianmoucv/tools.py
tianmoucv/data/__init__.py
tianmoucv/data/singlePathwayDecoder.py
tianmoucv/data/tianmoucData.py
tianmoucv/data/tianmoucDataSampleParser.py
tianmoucv/data/tianmoucData_basic.py
tianmoucv/data/tianmoucData_pcie.py
tianmoucv/data/blc/__init__.py
tianmoucv/isp/__init__.py
tianmoucv/isp/awb.py
tianmoucv/isp/isp_basic.py
tianmoucv/isp/transform.py
tianmoucv/isp/weightedGE.py
tianmoucv/nn/__init__.py
tianmoucv/nn/unet_modules.py
tianmoucv/proc/__init__.py
tianmoucv/proc/denoise/__init__.py
tianmoucv/proc/denoise/dn_args_generator.py
tianmoucv/proc/features/__init__.py
tianmoucv/proc/features/diff.py
tianmoucv/proc/nn/__init__.py
tianmoucv/proc/nn/nature_code.py
tianmoucv/proc/nn/spy_modules.py
tianmoucv/proc/nn/unet_modules.py
tianmoucv/proc/nn/utils.py
tianmoucv/proc/opticalflow/__init__.py
tianmoucv/proc/opticalflow/basic.py
tianmoucv/proc/opticalflow/estimator.py
tianmoucv/proc/opticalflow/spy_net.py
tianmoucv/proc/reconstruct/__init__.py
tianmoucv/proc/reconstruct/basic.py
tianmoucv/proc/reconstruct/fusion.py
tianmoucv/proc/reconstruct/integration.py
tianmoucv/proc/reconstruct/original.py
tianmoucv/proc/reconstruct/tiny_unet.py
tianmoucv/proc/tracking/__init__.py
tianmoucv/proc/tracking/feature_tracker.py
tianmoucv/rdp_pcie/CMakeLists.txt
tianmoucv/rdp_pcie/ReadMe.md
tianmoucv/rdp_pcie/__init__.py
tianmoucv/rdp_pcie/compile_pybind.bat
tianmoucv/rdp_pcie/compile_pybind.sh
tianmoucv/rdp_pcie/lyncam_compact_data.cpp
tianmoucv/rdp_pcie/rod_compress.cpp
tianmoucv/rdp_pcie/rod_decoder_py.cpp
tianmoucv/rdp_pcie/rod_decoder_py.cpython-313-x86_64-linux-gnu.so
tianmoucv/rdp_usb/CMakeLists.txt
tianmoucv/rdp_usb/ReadMe.md
tianmoucv/rdp_usb/__init__.py
tianmoucv/rdp_usb/compile_pybind.bat
tianmoucv/rdp_usb/compile_pybind.sh
tianmoucv/rdp_usb/merge_splited.py
tianmoucv/rdp_usb/rod_decoder_py.cpp
tianmoucv/rdp_usb/rod_decoder_py.cpython-313-x86_64-linux-gnu.so
tianmoucv/rdp_usb/try_pcie2usb_conv.py
tianmoucv/rdp_usb/try_usb_data.py
tianmoucv-0.3.5.0.dist-info/licenses/LICENSE
tianmoucv-0.3.5.0.dist-info/METADATA
tianmoucv-0.3.5.0.dist-info/WHEEL
tianmoucv-0.3.5.0.dist-info/top_level.txt
tianmoucv-0.3.5.0.dist-info/RECORD
